{"elapsed":"0.391","endpoint-url":"http://inspire.halton.gov.uk/geoserver/wfs?SERVICE=WFS&REQUEST=GetFeature&VERSION=2.0.0&TYPENAME=inspire:conservation_areas_polygon","entry-date":"2022-04-06T00:05:47.182460","request-headers":{"Accept":"*/*","Accept-Encoding":"gzip, deflate","Connection":"keep-alive","User-Agent":"DLUHC Digital Land"},"response-headers":{"Content-Encoding":"gzip","Content-Length":"372","Content-Type":"application/xml","Date":"Wed, 06 Apr 2022 00:08:39 GMT","Server":"Microsoft-IIS/8.5","Strict-Transport-Security":"max-age=31536000","X-Frame-Options":"SAMEORIGIN","X-Powered-By":"ARR/3.0"},"ssl-verify":true,"status":"400"}