{"elapsed":"1.202","endpoint-url":"https://maps.stockport.gov.uk/ishare5.0.web/getows.ashx?mapsource=smbc/stockport_inspire&TypeName=conservation_areas&version=1.1.0&request=GetFeature&service=WFS","entry-date":"2023-09-03T00:05:58.464882","request-headers":{"Accept":"*/*","Accept-Encoding":"gzip, deflate","Connection":"keep-alive","User-Agent":"DLUHC Digital Land"},"response-headers":{"Connection":"keep-alive","Content-Type":"application/xml","Date":"Sun, 03 Sep 2023 00:17:20 GMT","Server":"AmazonS3","Transfer-Encoding":"chunked","Via":"1.1 666c2260eba58c2b69ea2e6ef70667be.cloudfront.net (CloudFront)","X-Amz-Cf-Id":"YzSAdEC_WmzMOs-m6AjuDu_h4wscgmH_Y0KpSc6BNDs_V3ufdmy04A==","X-Amz-Cf-Pop":"LAX50-P2","X-Cache":"Error from cloudfront"},"ssl-verify":true,"status":"403"}