{"elapsed":"1.769","endpoint-url":"https://www.stalbans.gov.uk/sites/default/files/documents/publications/planning-building-control/Agile/Conservation_Area_Documentation_Dataset.csv","entry-date":"2024-02-13T00:05:42.512465","request-headers":{"Accept":"*/*","Accept-Encoding":"gzip, deflate","Connection":"keep-alive","User-Agent":"DLUHC Digital Land"},"resource":"33709f172535753ebc740a95556bea4d1aefcc3b4a27f74f6b47d0d0a9bd95a3","response-headers":{"accept-ranges":"bytes","cache-control":"max-age=1209600","content-length":"11548616","content-type":"text/csv","date":"Tue, 13 Feb 2024 00:24:06 GMT","etag":"\"b037c8-609ca17a23bda\"","expires":"Tue, 27 Feb 2024 00:24:06 GMT","last-modified":"Fri, 10 Nov 2023 10:50:44 GMT","referrer-policy":"strict-origin-when-cross-origin","server":"Apache","set-cookie":"HACIVIC4=app-47_897e; path=/; HttpOnly; Secure; SameSite=None","strict-transport-security":"max-age=31536000; includeSubdomains; preload","vary":"X-Forwarded-Protocol","x-content-type-options":"nosniff","x-frame-options":"SAMEORIGIN","x-xss-protection":"1"},"ssl-verify":true,"status":"200"}