{"elapsed":"3.731","endpoint-url":"https://maps.buckscc.gov.uk/arcgis/services/PLANNING/RIPA_BOPS/MapServer/WFSServer?service=WFS&version=2.0.0&request=GetFeature&typeName=PLANNING_RIPA_BOPS:Conservation_Areas&outputFormat=GML2","entry-date":"2024-02-24T00:03:51.974291","request-headers":{"Accept":"*/*","Accept-Encoding":"gzip, deflate","Connection":"keep-alive","User-Agent":"DLUHC Digital Land"},"resource":"51665daeaeece9136f674e024bd5095a1f8a69cf7a3c879ff016006884bbbb98","response-headers":{"Content-Type":"application/xml;charset=UTF-8","Date":"Sat, 24 Feb 2024 00:20:34 GMT","Keep-Alive":"timeout=60","Server":"","Transfer-Encoding":"chunked, chunked","X-Content-Type-Options":"nosniff","X-XSS-Protection":"1; mode=block","accept":"text/html, image/gif, image/jpeg, *; q=.2, */*; q=.2","cache-control":"no-cache","connection":"keep-alive, keep-alive","host":"maps.buckscc.gov.uk","pragma":"no-cache","referer":"0dc0a377-c86e-4454-a4b4-e1de5148c398","referrer":"0dc0a377-c86e-4454-a4b4-e1de5148c398","response_buffer_size":"8192","response_character_encoding":"UTF-8","response_content_type":"application/xml","response_status_code":"200","user-agent":"Java/11.0.6"},"ssl-verify":true,"status":"200"}