{"elapsed":"0.936","endpoint-url":"https://maps.dartmoor.gov.uk/geoserver/inspire/ows?service=WFS&version=1.0.0&request=GetFeature&typeName=inspire_conareas","entry-date":"2020-12-20T01:00:04.717777","request-headers":{"Accept":"*/*","Accept-Encoding":"gzip, deflate","Connection":"keep-alive","User-Agent":"Digital Land data collector"},"resource":"bf425f84d28adbc7b86d3f25187fb5065cb2b5bc077d01f67112b3d29c2d07bf","response-headers":{"Connection":"Keep-Alive","Content-Disposition":"inline; filename=geoserver-GetFeature.text","Content-Encoding":"gzip","Content-Type":"text/xml; subtype=gml/2.1.2","Date":"Sun, 20 Dec 2020 01:03:15 GMT","Keep-Alive":"timeout=5, max=100","Server":"Apache-Coyote/1.1","Transfer-Encoding":"chunked","X-Frame-Options":"SAMEORIGIN"},"ssl-verify":true,"status":"200"}