{"bytes":167265,"elapsed":"1.107","endpoint-url":"http://www.mapping.cityoflondon.gov.uk/arcgis/services/INSPIRE/MapServer/WFSServer?SERVICE=WFS&REQUEST=GetFeature&VERSION=2.0.0&TYPENAME=INSPIRE:Conservation_Areas","entry-date":"2021-03-31T00:18:03.614318","request-headers":{"Accept":"*/*","Accept-Encoding":"gzip, deflate","Connection":"keep-alive","User-Agent":"Digital Land"},"resource":"7e3bb6b33294e828bf5d9b2416163efc06a5220d85dad93e2e952f96abbb93ce","response-headers":{"Cache-Control":"private","Content-Encoding":"gzip","Content-Length":"37561","Content-Type":"application/xml","Date":"Wed, 31 Mar 2021 00:18:52 GMT","Server":"","X-AspNet-Version":"4.0.30319","X-Powered-By":"ASP.NET"},"ssl-verify":true,"status":"200"}