{"elapsed":"1.023","endpoint-url":"http://www.mapping.cityoflondon.gov.uk/arcgis/services/INSPIRE/MapServer/WFSServer?SERVICE=WFS&REQUEST=GetFeature&VERSION=2.0.0&TYPENAME=INSPIRE:Conservation_Areas","entry-date":"2021-03-20T00:56:21.756651","request-headers":{"Accept":"*/*","Accept-Encoding":"gzip, deflate","Connection":"keep-alive","User-Agent":"Digital Land"},"resource":"f3cc6c2d4971653ea2fdb2e0fe1fcbcea44092076597b187250fc652ff82c214","response-headers":{"Cache-Control":"private","Content-Encoding":"gzip","Content-Length":"37733","Content-Type":"application/xml","Date":"Sat, 20 Mar 2021 00:57:12 GMT","Server":"","X-AspNet-Version":"4.0.30319","X-Powered-By":"ASP.NET"},"ssl-verify":true,"status":"200"}