{"elapsed":"0.733","endpoint-url":"https://maps.stockport.gov.uk/ishare5.0.web/getows.ashx?mapsource=smbc/stockport_inspire&TypeName=conservation_areas&version=1.1.0&request=GetFeature&service=WFS","entry-date":"2023-12-07T00:04:54.605904","request-headers":{"Accept":"*/*","Accept-Encoding":"gzip, deflate","Connection":"keep-alive","User-Agent":"DLUHC Digital Land"},"response-headers":{"Connection":"keep-alive","Content-Type":"application/xml","Date":"Thu, 07 Dec 2023 00:19:12 GMT","Server":"AmazonS3","Transfer-Encoding":"chunked","Via":"1.1 46aba6b15045c2b494b2c260627fbfda.cloudfront.net (CloudFront)","X-Amz-Cf-Id":"efWCM2g_VQoNINZNiw2kuGNl3rridGd37jSsPjEzWyBnKI60FRnwxQ==","X-Amz-Cf-Pop":"IAD89-C2","X-Cache":"Error from cloudfront"},"ssl-verify":true,"status":"403"}