{"elapsed":"6.988","endpoint-url":"http://map.cornwall.gov.uk/arcgis/services/inspire/inspire_historic/MapServer/WFSServer?service=WFS&version=1.1.0&Request=GetFeature&TypeName=inspire_inspire_historic:conservation_areas","entry-date":"2021-02-12T00:49:51.359578","request-headers":{"Accept":"*/*","Accept-Encoding":"gzip, deflate","Connection":"keep-alive","User-Agent":"Digital Land"},"resource":"7d811dd70790c31f3783e673b8bcc5d6d1e7267466fdf25bd706476319a43802","response-headers":{"Cache-Control":"private","Content-Length":"3701922","Content-Type":"text/xml; subtype=gml/3.1.1","Date":"Fri, 12 Feb 2021 00:49:58 GMT","Expires":"Thu, 01 Jan 1970 01:00:00 GMT","Server":"Microsoft-IIS/8.5, ","Set-Cookie":"BNI_persistence=-oMuwJWTY8xe9gAXchZ7LZIV_9pUzvcHQcZgscjjFqYpNbMUcmeRl96jaP1fpBswrBql7Aqe5Pfa5Y6FgV6ATg==; Path=/","X-AspNet-Version":"4.0.30319","X-Powered-By":"ASP.NET","X-UA-Compatible":"IE=Edge"},"ssl-verify":true,"status":"200"}