{"elapsed":"0.785","endpoint-url":"https://apps.bracknell-forest.gov.uk/PublicWebsiteNew/files/DataGOVUK/ConservationAreas.zip","entry-date":"2023-07-26T00:05:53.788659","request-headers":{"Accept":"*/*","Accept-Encoding":"gzip, deflate","Connection":"keep-alive","User-Agent":"DLUHC Digital Land"},"response-headers":{"Connection":"keep-alive","Content-Encoding":"gzip","Content-Type":"text/html","Date":"Wed, 26 Jul 2023 00:11:03 GMT","Server":"nginx/1.18.0 (Ubuntu)","Transfer-Encoding":"chunked"},"ssl-verify":true,"status":"404"}