{"elapsed":"0.4","endpoint-url":"http://inspire.halton.gov.uk/geoserver/wfs?SERVICE=WFS&REQUEST=GetFeature&VERSION=2.0.0&TYPENAME=inspire:conservation_areas_polygon","entry-date":"2021-06-19T01:03:31.886844","request-headers":{"Accept":"*/*","Accept-Encoding":"gzip, deflate","Connection":"keep-alive","User-Agent":"Digital Land"},"response-headers":{"Content-Encoding":"gzip","Content-Length":"373","Content-Type":"application/xml","Date":"Sat, 19 Jun 2021 01:09:33 GMT","Server":"Microsoft-IIS/8.5","Strict-Transport-Security":"max-age=31536000","X-Frame-Options":"SAMEORIGIN","X-Powered-By":"ARR/3.0"},"ssl-verify":true,"status":"400"}