{"elapsed":"0.073","endpoint-url":"http://inspire.misoportal.com/geoserver/south_northamptonshire_district_council_conservation_areas/wfs?request=GetFeature&TypeName=south_northamptonshire_district_council_conservation_areas","entry-date":"2021-07-29T01:02:59.542674","request-headers":{"Accept":"*/*","Accept-Encoding":"gzip, deflate","Connection":"keep-alive","User-Agent":"Digital Land"},"response-headers":{"Connection":"Keep-Alive","Content-Length":"361","Content-Type":"text/html; charset=iso-8859-1","Date":"Thu, 29 Jul 2021 01:11:08 GMT","Keep-Alive":"timeout=5, max=99","Server":"Apache/2.4.7 (Ubuntu)"},"ssl-verify":true,"status":"403"}