{"elapsed":"0.088","endpoint-url":"http://inspire.misoportal.com/geoserver/peak_district_national_park_pdnpa-conservationarea/wfs?SERVICE=WFS&REQUEST=GetFeature&VERSION=2.0.0&TYPENAME=peak_district_national_park_pdnpa-conservationarea","entry-date":"2023-12-30T00:04:10.527672","request-headers":{"Accept":"*/*","Accept-Encoding":"gzip, deflate","Connection":"keep-alive","User-Agent":"DLUHC Digital Land"},"response-headers":{"Connection":"Keep-Alive","Content-Length":"349","Content-Type":"text/html; charset=iso-8859-1","Date":"Sat, 30 Dec 2023 00:07:55 GMT","Keep-Alive":"timeout=5, max=99","Server":"Apache/2.4.7 (Ubuntu)"},"ssl-verify":true,"status":"404"}