{"elapsed":"0.796","endpoint-url":"https://maps.stockport.gov.uk/ishare5.0.web/getows.ashx?mapsource=smbc/stockport_inspire&TypeName=conservation_areas&version=1.1.0&request=GetFeature&service=WFS","entry-date":"2023-06-17T00:04:30.101407","request-headers":{"Accept":"*/*","Accept-Encoding":"gzip, deflate","Connection":"keep-alive","User-Agent":"DLUHC Digital Land"},"response-headers":{"Connection":"keep-alive","Content-Type":"application/xml","Date":"Sat, 17 Jun 2023 00:15:36 GMT","Server":"AmazonS3","Transfer-Encoding":"chunked","Via":"1.1 46aba6b15045c2b494b2c260627fbfda.cloudfront.net (CloudFront)","X-Amz-Cf-Id":"hI1fjGQkniaJxbL3SV0gGfv4YeZzkv8mgvC29SqBXKJ_X_ltGUeFYA==","X-Amz-Cf-Pop":"IAD89-C2","X-Cache":"Error from cloudfront"},"ssl-verify":true,"status":"403"}