{"elapsed":"0.325","endpoint-url":"https://raw.githubusercontent.com/digital-land/conservation-area-collection/main/data/Southwark/Southwark%20Conservation%20Areas.gpkg","entry-date":"2023-08-16T00:04:38.758392","request-headers":{"Accept":"*/*","Accept-Encoding":"gzip, deflate","Connection":"keep-alive","User-Agent":"DLUHC Digital Land"},"resource":"b9503f86a1e0c5e02c1fa5b42b8d84c63b1cca421813dfc44c0f1bf7b59e5d74","response-headers":{"Accept-Ranges":"bytes","Access-Control-Allow-Origin":"*","Cache-Control":"max-age=300","Connection":"keep-alive","Content-Length":"516096","Content-Security-Policy":"default-src 'none'; style-src 'unsafe-inline'; sandbox","Content-Type":"application/octet-stream","Cross-Origin-Resource-Policy":"cross-origin","Date":"Wed, 16 Aug 2023 00:18:48 GMT","ETag":"W/\"bd3e38098b01a893b7988961620ac7b998994700da9ebbe6bdcff2cc81d7d7ee\"","Expires":"Wed, 16 Aug 2023 00:23:48 GMT","Source-Age":"0","Strict-Transport-Security":"max-age=31536000","Vary":"Authorization,Accept-Encoding,Origin","Via":"1.1 varnish","X-Cache":"MISS","X-Cache-Hits":"0","X-Content-Type-Options":"nosniff","X-Fastly-Request-ID":"6634a2db3cc71b7289bba208948556f8d5dc6cbe","X-Frame-Options":"deny","X-GitHub-Request-Id":"E9F0:5B94:5A1EAC:69A1B5:64DC15E7","X-Served-By":"cache-dfw-kdfw8210081-DFW","X-Timer":"S1692145128.315849,VS0,VE153","X-XSS-Protection":"1; mode=block"},"ssl-verify":true,"status":"200"}