{"datetime":"2020-09-30T15:21:41.686431","elapsed":"0.266","request-headers":{"Accept":"*/*","Accept-Encoding":"gzip, deflate","Connection":"keep-alive","User-Agent":"Digital Land data collector"},"resource":"5122c0abd44c0cc8510bdb75f428ef1e0ffb846e721d57fcac2722b04e50dc21","response-headers":{"Connection":"Keep-Alive","Content-Disposition":"inline; filename=geoserver-GetFeature.text","Content-Encoding":"gzip","Content-Type":"text/xml; subtype=gml/3.2","Date":"Wed, 30 Sep 2020 15:27:39 GMT","Keep-Alive":"timeout=5, max=99","Server":"Apache-Coyote/1.1","Transfer-Encoding":"chunked"},"status":"200","url":"http://inspire.misoportal.com/geoserver/north_east_derbyshire_ned_conservation_areas/wfs?request=GetFeature&TypeName=north_east_derbyshire_ned_conservation_areas"}