{"datetime":"2020-09-30T15:21:41.686431","elapsed":"0.382","request-headers":{"Accept":"*/*","Accept-Encoding":"gzip, deflate","Connection":"keep-alive","User-Agent":"Digital Land data collector"},"response-headers":{"Accept-Ranges":"bytes","Age":"3014","Connection":"keep-alive","Content-Length":"673","Content-Type":"text/html","Date":"Wed, 30 Sep 2020 14:24:54 GMT","ETag":"\"0ae7537897d61:0\"","Last-Modified":"Wed, 30 Sep 2020 09:01:00 GMT"},"status":"200","url":"http://www.mapping.cityoflondon.gov.uk/arcgis/services/INSPIRE/MapServer/WFSServer?SERVICE=WFS&REQUEST=GetFeature&VERSION=2.0.0&TYPENAME=INSPIRE:Conservation_Areas"}