{"bytes":194431,"elapsed":"0.786","endpoint-url":"http://mapping.dudley.gov.uk/getows.ashx?mapsource=DMBC/inspire&service=WFS&version=1.1.0&Request=GetFeature&TypeName=conservation_areas","entry-date":"2021-06-06T01:38:41.035733","request-headers":{"Accept":"*/*","Accept-Encoding":"gzip, deflate","Connection":"keep-alive","User-Agent":"Digital Land"},"resource":"69066cd4e08c8fe57c8fc3fe35d4cdf24e74353f15e1a7cd9a754b35af65b5be","response-headers":{"Access-Control-Allow-Headers":"Accept,ContentType,X-Requested-With","Access-Control-Allow-Methods":"GET, OPTIONS","Access-Control-Allow-Origin":"*","Cache-Control":"private","Content-Length":"194532","Content-Type":"text/xml; subtype=gml/3.1.1; charset=utf-8","Date":"Sun, 06 Jun 2021 01:41:47 GMT","Set-Cookie":"TS01395a7b=0104e7c062ad81bae245f11fde842bc15f05af601b6ca53cd1066ad9cd0e5f5f9acf6ff345f9b24d6d50e433074c323516fb0e5f8a; Path=/; Domain=.mapping.dudley.gov.uk; HTTPOnly","X-UA-Compatible":"IE=Edge"},"ssl-verify":true,"status":"200"}