{"elapsed":"0.702","endpoint-url":"https://maps.stockport.gov.uk/ishare5.0.web/getows.ashx?mapsource=smbc/stockport_inspire&TypeName=conservation_areas&version=1.1.0&request=GetFeature&service=WFS","entry-date":"2023-10-17T00:06:05.502242","request-headers":{"Accept":"*/*","Accept-Encoding":"gzip, deflate","Connection":"keep-alive","User-Agent":"DLUHC Digital Land"},"response-headers":{"Connection":"keep-alive","Content-Type":"application/xml","Date":"Tue, 17 Oct 2023 00:19:13 GMT","Server":"AmazonS3","Transfer-Encoding":"chunked","Via":"1.1 966d01179c7098b0cf2a20ba8c352dee.cloudfront.net (CloudFront)","X-Amz-Cf-Id":"eb6t4UcfLl3FO-SqPIQqxyHCwkw6LZvPspq2p7LQTUVPR9ZIvgIt3g==","X-Amz-Cf-Pop":"IAD89-C2","X-Cache":"Error from cloudfront"},"ssl-verify":true,"status":"403"}