{"bytes":5648384,"elapsed":"1.501","endpoint-url":"https://data.london.gov.uk/download/conservation_areas/b38eae6d-10db-4c79-afdd-dd97ae367b8b/Conservation_Areas.gpkg","entry-date":"2021-05-20T01:09:42.068340","request-headers":{"Accept":"*/*","Accept-Encoding":"gzip, deflate","Connection":"keep-alive","User-Agent":"Digital Land"},"resource":"f617d13ef7ff061424ec50ed641f05779797ff03beb2cde6935f2a307c01ab44","response-headers":{"Accept-Ranges":"bytes","Content-Length":"5648384","Content-Type":"application/octet-stream","Date":"Thu, 20 May 2021 01:09:44 GMT","ETag":"\"10ba03ae5e78bd094ee4de36572d73e6\"","Last-Modified":"Fri, 30 Aug 2019 15:17:25 GMT","Server":"AmazonS3","x-amz-id-2":"o4u3A9RygFZaSPuOTObxRt2wpauOcQrKbdRw6RUEHTUF9r3EvpmiscvXPja4c0Fk2LX8lja+Pws=","x-amz-request-id":"FB19C2PRJW39J9N7","x-amz-version-id":"KPDRGqyGA06LcUGNaD8.k_Fgwo2HfQYf"},"ssl-verify":true,"status":"200"}