{"elapsed":"1.532","endpoint-url":"http://www.mapping.cityoflondon.gov.uk/arcgis/services/INSPIRE/MapServer/WFSServer?SERVICE=WFS&REQUEST=GetFeature&VERSION=2.0.0&TYPENAME=INSPIRE:Conservation_Areas","entry-date":"2021-08-19T00:56:35.899802","request-headers":{"Accept":"*/*","Accept-Encoding":"gzip, deflate","Connection":"keep-alive","User-Agent":"Digital Land"},"resource":"2122e5518f88fad38c1a2f7f3b5f3c2ceb4a0cf5890fdc7606e9d9e927be22ea","response-headers":{"Cache-Control":"private","Content-Encoding":"gzip","Content-Length":"37897","Content-Type":"application/xml","Date":"Thu, 19 Aug 2021 00:58:24 GMT","Server":"","X-AspNet-Version":"4.0.30319","X-Powered-By":"ASP.NET"},"ssl-verify":true,"status":"200"}