{"elapsed":"0.753","endpoint-url":"https://maps.stockport.gov.uk/ishare5.0.web/getows.ashx?mapsource=smbc/stockport_inspire&TypeName=conservation_areas&version=1.1.0&request=GetFeature&service=WFS","entry-date":"2022-06-22T00:06:40.834816","request-headers":{"Accept":"*/*","Accept-Encoding":"gzip, deflate","Connection":"keep-alive","User-Agent":"DLUHC Digital Land"},"response-headers":{"Connection":"keep-alive","Content-Type":"application/xml","Date":"Wed, 22 Jun 2022 00:12:45 GMT","Server":"AmazonS3","Transfer-Encoding":"chunked","Via":"1.1 ea419f8269940bd7231c70acd36c430c.cloudfront.net (CloudFront)","X-Amz-Cf-Id":"JaCvI6SlEDJljjLf2mUq1Ag6ljytSnLnEcGLybqT_DRTkWW-ff4SZw==","X-Amz-Cf-Pop":"YUL62-C2","X-Cache":"Error from cloudfront"},"ssl-verify":true,"status":"403"}