{"elapsed":"2.85","endpoint-url":"https://data.london.gov.uk/download/conservation_areas/b38eae6d-10db-4c79-afdd-dd97ae367b8b/Conservation_Areas.gpkg","entry-date":"2023-03-13T00:05:19.530874","request-headers":{"Accept":"*/*","Accept-Encoding":"gzip, deflate","Connection":"keep-alive","User-Agent":"DLUHC Digital Land"},"resource":"f617d13ef7ff061424ec50ed641f05779797ff03beb2cde6935f2a307c01ab44","response-headers":{"Accept-Ranges":"bytes","Content-Length":"5648384","Content-Type":"application/octet-stream","Date":"Mon, 13 Mar 2023 00:06:31 GMT","ETag":"\"10ba03ae5e78bd094ee4de36572d73e6\"","Last-Modified":"Fri, 30 Aug 2019 15:17:25 GMT","Server":"AmazonS3","x-amz-id-2":"fa1WHAiqKRxNlSWiJ+Cg/w2MYHHzBpT3FqczpZ9agH0a3JUEyNMELguzaSCsCIhyF3mP660p6o0=","x-amz-request-id":"JYEYBBYQ7ZQ0KZSR","x-amz-version-id":"KPDRGqyGA06LcUGNaD8.k_Fgwo2HfQYf"},"ssl-verify":true,"status":"200"}