{"elapsed":"1.553","endpoint-url":"http://www.mapping.cityoflondon.gov.uk/arcgis/services/INSPIRE/MapServer/WFSServer?SERVICE=WFS&REQUEST=GetFeature&VERSION=2.0.0&TYPENAME=INSPIRE:Conservation_Areas","entry-date":"2021-07-30T01:06:28.515849","request-headers":{"Accept":"*/*","Accept-Encoding":"gzip, deflate","Connection":"keep-alive","User-Agent":"Digital Land"},"resource":"d0cd3fe50c1df3f865090a84fceb09c12fe69d93aa59d20cfcd7a305d611f3f8","response-headers":{"Cache-Control":"private","Content-Encoding":"gzip","Content-Length":"37673","Content-Type":"application/xml","Date":"Fri, 30 Jul 2021 01:08:07 GMT","Server":"","X-AspNet-Version":"4.0.30319","X-Powered-By":"ASP.NET"},"ssl-verify":true,"status":"200"}