{"elapsed":"5.387","endpoint-url":"http://maps.southoxon.gov.uk/arcgis/services/Open_data_southoxon/MapServer/WFSServer?request=GetFeature&service=WFS&TypeName=conservation_areas","entry-date":"2022-12-22T00:04:53.938427","request-headers":{"Accept":"*/*","Accept-Encoding":"gzip, deflate","Connection":"keep-alive","User-Agent":"DLUHC Digital Land"},"resource":"07b84eadda99567f835a1f5919bd0a2ab48291932ad7cfaae33032ffb48744b3","response-headers":{"Cache-Control":"private","Content-Encoding":"gzip","Content-Length":"291022","Content-Type":"text/xml","Date":"Thu, 22 Dec 2022 00:05:28 GMT","Server":"Microsoft-IIS/8.5, ","Set-Cookie":"BIGipServer~TEN-5C-CVW_Partition~Pool_5C_SAV_ArcGis_ext_10.124.125.54_80=rd106o00000000000000000000ffff0a7c7d02o80; path=/; Httponly","X-AspNet-Version":"2.0.50727","X-Powered-By":"ASP.NET"},"ssl-verify":true,"status":"200"}