{"datetime":"2020-09-23T16:59:48.149067","elapsed":"0.198","request-headers":{"Accept":"*/*","Accept-Encoding":"gzip, deflate","Connection":"keep-alive","User-Agent":"Digital Land data collector"},"resource":"b4a75b0ccd2133f155f65c895cf6a9aeb74bfa570e124afc2bf4e6afc8cdf550","response-headers":{"Connection":"Keep-Alive","Content-Disposition":"inline; filename=geoserver-GetFeature.text","Content-Encoding":"gzip","Content-Type":"text/xml; subtype=gml/3.2","Date":"Wed, 23 Sep 2020 17:05:53 GMT","Keep-Alive":"timeout=5, max=99","Server":"Apache-Coyote/1.1","Transfer-Encoding":"chunked"},"status":"200","url":"http://inspire.misoportal.com/geoserver/north_east_derbyshire_ned_conservation_areas/wfs?request=GetFeature&TypeName=north_east_derbyshire_ned_conservation_areas"}