{"elapsed":"0.73","endpoint-url":"https://datamillnorth.org/download/conservation-areas/177d2543-b8d2-4c5f-9ab2-6fa47188396f/conservation_areas_2012.kml","entry-date":"2023-02-01T00:06:06.907761","request-headers":{"Accept":"*/*","Accept-Encoding":"gzip, deflate","Connection":"keep-alive","User-Agent":"DLUHC Digital Land"},"response-headers":{"Connection":"keep-alive","Content-Encoding":"gzip","Content-Type":"text/plain;charset=UTF-8","Date":"Wed, 01 Feb 2023 00:10:41 GMT","Server":"nginx","Transfer-Encoding":"chunked","Via":"1.1 23902d8ef9680db023f27a4c4f37e390.cloudfront.net (CloudFront)","X-Amz-Cf-Id":"5ILGsV_jwOGCJ63h0ztJsqv935BRJXJo2oG3btm7kMPS-GTlt2yFRw==","X-Amz-Cf-Pop":"HIO50-C2","X-Cache":"Error from cloudfront","X-Powered-By":"PHP/7.2.34"},"ssl-verify":true,"status":"404"}