{"elapsed":"2.167","endpoint-url":"https://data.london.gov.uk/download/conservation_areas/b38eae6d-10db-4c79-afdd-dd97ae367b8b/Conservation_Areas.gpkg","entry-date":"2022-10-13T00:07:34.951422","request-headers":{"Accept":"*/*","Accept-Encoding":"gzip, deflate","Connection":"keep-alive","User-Agent":"DLUHC Digital Land"},"resource":"f617d13ef7ff061424ec50ed641f05779797ff03beb2cde6935f2a307c01ab44","response-headers":{"Accept-Ranges":"bytes","Content-Length":"5648384","Content-Type":"application/octet-stream","Date":"Thu, 13 Oct 2022 00:09:43 GMT","ETag":"\"10ba03ae5e78bd094ee4de36572d73e6\"","Last-Modified":"Fri, 30 Aug 2019 15:17:25 GMT","Server":"AmazonS3","x-amz-id-2":"9ThXIAHjNu3NgdvDmcErw1ECINb7MXd8D5BV7S/j3CYNup78a2WJXr4E//I0mT2VVfcNlVicU5c=","x-amz-request-id":"1CEBDVYRS5FMRW3K","x-amz-version-id":"KPDRGqyGA06LcUGNaD8.k_Fgwo2HfQYf"},"ssl-verify":true,"status":"200"}