{"elapsed":"0.624","endpoint-url":"http://data-gedlingbc.opendata.arcgis.com/datasets/76565d3f82ce41fbb52745728cdc5d52_0.geojson","entry-date":"2020-12-19T00:57:39.621944","request-headers":{"Accept":"*/*","Accept-Encoding":"gzip, deflate","Connection":"keep-alive","User-Agent":"Digital Land data collector"},"response-headers":{"Access-Control-Allow-Origin":"*","Connection":"keep-alive","Content-Length":"243","Content-Type":"application/json; charset=utf-8","Date":"Sat, 19 Dec 2020 01:01:08 GMT","ETag":"W/\"f3-FZ5BiBgkz1OGmdv/yAHnyMFOlWE\"","Server":"openresty","X-Powered-By":"Express"},"ssl-verify":true,"status":"500"}