{"bytes":194431,"elapsed":"2.296","endpoint-url":"http://mapping.dudley.gov.uk/getows.ashx?mapsource=DMBC/inspire&service=WFS&version=1.1.0&Request=GetFeature&TypeName=conservation_areas","entry-date":"2021-05-17T01:12:54.302711","request-headers":{"Accept":"*/*","Accept-Encoding":"gzip, deflate","Connection":"keep-alive","User-Agent":"Digital Land"},"resource":"69066cd4e08c8fe57c8fc3fe35d4cdf24e74353f15e1a7cd9a754b35af65b5be","response-headers":{"Access-Control-Allow-Headers":"Accept,ContentType,X-Requested-With","Access-Control-Allow-Methods":"GET, OPTIONS","Access-Control-Allow-Origin":"*","Cache-Control":"private","Content-Length":"194532","Content-Type":"text/xml; subtype=gml/3.1.1; charset=utf-8","Date":"Mon, 17 May 2021 01:16:23 GMT","Set-Cookie":"TS01395a7b=0104e7c0625dcee2439b8f05805aa99bce5599c00c3ae0240690f13dcb00c96f2bc80b569cadaf422d95213e381bf50653e60d1fa8; Path=/; Domain=.mapping.dudley.gov.uk; HTTPOnly","X-UA-Compatible":"IE=Edge"},"ssl-verify":true,"status":"200"}