{"elapsed":"0.651","endpoint-url":"https://opendata.camden.gov.uk/api/geospatial/hcxu-iumk?method=export&format=KML","entry-date":"2022-06-26T00:07:16.212586","request-headers":{"Accept":"*/*","Accept-Encoding":"gzip, deflate","Connection":"keep-alive","User-Agent":"DLUHC Digital Land"},"response-headers":{"Access-Control-Allow-Origin":"*","Age":"0","Cache-Control":"private, no-cache, must-revalidate","Connection":"keep-alive","Content-Encoding":"gzip","Content-Type":"application/json; charset=utf-8","Date":"Sun, 26 Jun 2022 00:13:54 GMT","Server":"nginx","Strict-Transport-Security":"max-age=31536000; includeSubDomains","Transfer-Encoding":"chunked","X-Error-Code":"not_found","X-Error-Message":"Not found","X-Socrata-Region":"aws-eu-west-1-prod","X-Socrata-RequestId":"f12e6385ea354548775f9a44052ee398"},"ssl-verify":true,"status":"404"}