{"elapsed":"1.068","endpoint-url":"http://www.mapping.cityoflondon.gov.uk/arcgis/services/INSPIRE/MapServer/WFSServer?SERVICE=WFS&REQUEST=GetFeature&VERSION=2.0.0&TYPENAME=INSPIRE:Conservation_Areas","entry-date":"2022-01-04T01:12:53.588350","request-headers":{"Accept":"*/*","Accept-Encoding":"gzip, deflate","Connection":"keep-alive","User-Agent":"DLUHC Digital Land"},"resource":"5237be11ac0708190cac435268b28d5288b96510459512ee18b66d9c35c26255","response-headers":{"Cache-Control":"private","Content-Encoding":"gzip","Content-Length":"37166","Content-Type":"application/xml","Date":"Tue, 04 Jan 2022 01:26:06 GMT","Server":"","X-AspNet-Version":"4.0.30319","X-Powered-By":"ASP.NET"},"ssl-verify":true,"status":"200"}